suction_nms.cp37-win_amd64.pyd
suction_nms-1.0.0.dist-info/LICENSE
suction_nms-1.0.0.dist-info/METADATA
suction_nms-1.0.0.dist-info/WHEEL
suction_nms-1.0.0.dist-info/top_level.txt
suction_nms-1.0.0.dist-info/RECORD
