Metadata-Version: 2.1
Name: suction-nms
Version: 1.0.0
Summary: suction pose non-maximum supression
Home-page: https://github.com/intrepidChw/suctionnms.git
Author: Hanwen Cao
Author-email: hwcao17@gmail.com
License: UNKNOWN
Platform: UNKNOWN
